[
    {
        "website" : {
            "title" : "Erick Xavier | Front End Developer | Usability Expert"
        },
        "header" : {
            "title" : "Erick Xavier",
            "headline" : "Front End Developer | AngularJS, SASS/LESS, Bootstrap, jQuery",
            "menu" : {
                "aboutme" : "about me",
                "portfolio" : "portfolio",
                "experience" : "experience",
                "lab" : "lab",
                "blog" : "blog",
                "contact" : "contact"
            }
        },
        "owner" : {
            "title" : "A little about me",
            "description" : "Hi.<br><br>My name is Erick Xavier and I am a passionate Front End Developer with more than 10 years of experience.<br><br>I've delivered dozens of websites for fully satisfied clients and teams I've worked with. In my previous experience I've worked with offices all around the globe, including NYC, Rome, Bangalore, Mexico City and others. I'm experienced in HTML, CSS, JS and the frameworks jQuery, AngularJS, SASS and LESS. My focus, discipline and learning capacity care my most valuable assets.<br><br>In my free time I love to ride my motorcycle around my city and visit new places.<br><br>If you wish to present new opportunities or know more about me, please don't hesitate to contact me soon as you can."
        },
        "footer" : {
            "copyright": "&copy; 2015 <a href='https://github.com/ErickXavier/material-developer-website' target='_blank'>Creative Commons</a> Erick Xavier",
            "bottomline": "Made with &#x2661;."
        },
        "form" : {
            "name" : "Name",
            "email" : "Email",
            "message" : "Message",
            "send" : "Send"
        }
    }
]
